{
    "world": {
        "position": {
            "x": 0.0,
            "y": 0.0,
            "z": 0.0
        },
        "rotation": {
            "x": 0.0,
            "y": 0.0,
            "z": 0.0,
            "w": 0.0
        },
        "scale": {
            "x": 0.0,
            "y": 0.0,
            "z": 0.0
        }
    },
    "camera": {
        "backgroundColor": {
            "r": 0.4627451002597809,
            "g": 0.4627451002597809,
            "b": 0.4627451002597809,
            "a": 1.0
        },
        "transform": {
            "position": {
                "x": 0.0,
                "y": 0.0,
                "z": -2.0
            },
            "rotation": {
                "x": 0.0,
                "y": 0.0,
                "z": 0.0,
                "w": 1.0
            },
            "scale": {
                "x": 1.0,
                "y": 1.0,
                "z": 1.0
            }
        },
        "fieldOfView": 50.0,
        "orthographic": true
    },
    "shapes": [
        {
            "transform": {
                "position": {
                    "x": 0.2511707544326782,
                    "y": 0.4926544427871704,
                    "z": 0.40871739387512209
                },
                "rotation": {
                    "x": -0.5413624048233032,
                    "y": 0.25217461585998537,
                    "z": 0.4959595501422882,
                    "w": 0.630364179611206
                },
                "scale": {
                    "x": 0.05860308185219765,
                    "y": 0.05860308185219765,
                    "z": 0.05860308185219765
                }
            },
            "shapeFilename": "shapes-07",
            "spoutReceiverName": "",
            "shapeColor": {
                "r": 0.0,
                "g": 0.0,
                "b": 0.0,
                "a": 1.0
            },
            "audioReactiveScale": [
                0.0,
                0.0,
                0.0
            ],
            "audioReactiveStrength": 1.0,
            "story": {
                "title": "",
                "body": ""
            }
        },
        {
            "transform": {
                "position": {
                    "x": 0.18215805292129517,
                    "y": 0.38644611835479739,
                    "z": -0.3069715201854706
                },
                "rotation": {
                    "x": 0.10774863511323929,
                    "y": -0.3310227692127228,
                    "z": 0.07753437012434006,
                    "w": 0.9342390894889832
                },
                "scale": {
                    "x": 0.07658896595239639,
                    "y": 0.07658896595239639,
                    "z": 0.07658896595239639
                }
            },
            "shapeFilename": "shapes-07",
            "spoutReceiverName": "",
            "shapeColor": {
                "r": 0.0,
                "g": 0.0,
                "b": 0.0,
                "a": 1.0
            },
            "audioReactiveScale": [
                0.0,
                0.0,
                0.0
            ],
            "audioReactiveStrength": 1.0,
            "story": {
                "title": "",
                "body": ""
            }
        },
        {
            "transform": {
                "position": {
                    "x": -0.2209673821926117,
                    "y": -0.24054297804832459,
                    "z": -0.13938841223716737
                },
                "rotation": {
                    "x": -0.8833372592926025,
                    "y": 0.1683136373758316,
                    "z": -0.4116600751876831,
                    "w": 0.1480603814125061
                },
                "scale": {
                    "x": 0.07025975733995438,
                    "y": 0.07025975733995438,
                    "z": 0.07025975733995438
                }
            },
            "shapeFilename": "shapes-06",
            "spoutReceiverName": "",
            "shapeColor": {
                "r": 0.0,
                "g": 0.0,
                "b": 0.0,
                "a": 1.0
            },
            "audioReactiveScale": [
                0.0,
                0.0,
                0.0
            ],
            "audioReactiveStrength": 1.0,
            "story": {
                "title": "",
                "body": ""
            }
        },
        {
            "transform": {
                "position": {
                    "x": 0.16876846551895142,
                    "y": -0.4149571657180786,
                    "z": -0.00528949499130249
                },
                "rotation": {
                    "x": -0.9420340657234192,
                    "y": 0.013809561729431153,
                    "z": -0.3340744972229004,
                    "w": 0.027846120297908784
                },
                "scale": {
                    "x": 0.223042830824852,
                    "y": 0.223042830824852,
                    "z": 0.223042830824852
                }
            },
            "shapeFilename": "shapes-07",
            "spoutReceiverName": "",
            "shapeColor": {
                "r": 0.0,
                "g": 0.0,
                "b": 0.0,
                "a": 1.0
            },
            "audioReactiveScale": [
                0.0,
                0.0,
                0.0
            ],
            "audioReactiveStrength": 1.0,
            "story": {
                "title": "",
                "body": ""
            }
        },
        {
            "transform": {
                "position": {
                    "x": -0.43766987323760989,
                    "y": -0.4466034173965454,
                    "z": -0.46830856800079348
                },
                "rotation": {
                    "x": 0.2445298433303833,
                    "y": -0.3223860263824463,
                    "z": -0.46969661116600039,
                    "w": 0.7846384644508362
                },
                "scale": {
                    "x": 0.1602153480052948,
                    "y": 0.1602153480052948,
                    "z": 0.1602153480052948
                }
            },
            "shapeFilename": "shapes-07",
            "spoutReceiverName": "",
            "shapeColor": {
                "r": 0.0,
                "g": 0.0,
                "b": 0.0,
                "a": 1.0
            },
            "audioReactiveScale": [
                0.0,
                0.0,
                0.0
            ],
            "audioReactiveStrength": 1.0,
            "story": {
                "title": "",
                "body": ""
            }
        },
        {
            "transform": {
                "position": {
                    "x": 0.3975341320037842,
                    "y": 0.0979660153388977,
                    "z": -0.1953173577785492
                },
                "rotation": {
                    "x": 0.2685573399066925,
                    "y": 0.39716410636901858,
                    "z": -0.6403234004974365,
                    "w": 0.6001030802726746
                },
                "scale": {
                    "x": 0.2077353596687317,
                    "y": 0.2077353596687317,
                    "z": 0.2077353596687317
                }
            },
            "shapeFilename": "shapes-06",
            "spoutReceiverName": "",
            "shapeColor": {
                "r": 0.0,
                "g": 0.0,
                "b": 0.0,
                "a": 1.0
            },
            "audioReactiveScale": [
                0.0,
                0.0,
                0.0
            ],
            "audioReactiveStrength": 1.0,
            "story": {
                "title": "",
                "body": ""
            }
        },
        {
            "transform": {
                "position": {
                    "x": -0.4876689910888672,
                    "y": -0.16387078166007996,
                    "z": 0.0864974856376648
                },
                "rotation": {
                    "x": -0.5315559506416321,
                    "y": 0.7492707967758179,
                    "z": 0.11946914345026016,
                    "w": 0.37652188539505007
                },
                "scale": {
                    "x": 0.2465616762638092,
                    "y": 0.2465616762638092,
                    "z": 0.2465616762638092
                }
            },
            "shapeFilename": "shapes-06",
            "spoutReceiverName": "",
            "shapeColor": {
                "r": 0.0,
                "g": 0.0,
                "b": 0.0,
                "a": 1.0
            },
            "audioReactiveScale": [
                0.0,
                0.0,
                0.0
            ],
            "audioReactiveStrength": 1.0,
            "story": {
                "title": "",
                "body": ""
            }
        }
    ],
    "settings": {
        "fadeInDuration": 0.5,
        "fadeOutDuration": 1.0,
        "rotate2D": false,
        "randomWhiteCount": 0,
        "randomBlackCount": 7,
        "randomMinSize": 0.0,
        "randomMaxSize": 0.2657359838485718,
        "randomizeView": false,
        "randomCreateNewShapes": true,
        "randomFileCount": 1,
        "randomSelectionPercentage": 0.20000000298023225,
        "randomWhiteShapeFilenames": [
            "shapes-03",
            "shapes-04",
            "shapes-07"
        ],
        "randomBlackShapeFilenames": [
            "shapes-06",
            "shapes-07"
        ],
        "spaceNavigatorTranslationSensitivity": 0.30000001192092898,
        "spaceNavigatorRotationSensitivity": 10.0,
        "worldRotationSensitivity": -0.20000000298023225,
        "isAudioReactive": true,
        "overallAudioGain": 1.0,
        "framingData": {
            "showFrame2D": false,
            "showFrame3D": false,
            "showStencilCube": true,
            "frameColor": {
                "r": 0.0,
                "g": 0.0,
                "b": 0.0,
                "a": 0.501960813999176
            },
            "aspectRatio": 1.0
        },
        "antimatterGrid01": {
            "use": true,
            "amount": 1000.0,
            "lifetime": 1.0,
            "opacity": 0.10000000149011612
        },
        "antimatterGrid02": {
            "use": true,
            "amount": 1000.0,
            "lifetime": 1.0,
            "opacity": 0.10000000149011612
        },
        "antimatterGrid03": {
            "use": true,
            "amount": 1000.0,
            "lifetime": 1.0,
            "opacity": 0.10000000149011612
        },
        "antimatterGrid04": {
            "use": true,
            "amount": 1000.0,
            "lifetime": 1.0,
            "opacity": 0.10000000149011612
        },
        "ratingData": {
            "rating": -1
        }
    }
}